treestamps/__init__.py
treestamps/config.py
treestamps/grove.py
treestamps/printer.py
treestamps/tree/__init__.py
treestamps/tree/config.py
treestamps/tree/dump.py
treestamps/tree/get.py
treestamps/tree/init.py
treestamps/tree/load.py
treestamps/tree/set.py
treestamps-2.2.7.dist-info/WHEEL
treestamps-2.2.7.dist-info/METADATA
treestamps-2.2.7.dist-info/RECORD
