Metadata-Version: 2.4
Name: treestamps
Version: 2.2.7
Summary: Create timestamp records for recursive operations on directory trees.
Keywords: timestamps,library,recursive,directory
Author: AJ Slater
Author-email: AJ Slater <aj@slater.net>
License-Expression: GPL-3.0-only
Classifier: Development Status :: 5 - Production/Stable
Classifier: Environment :: Console
Classifier: Intended Audience :: Developers
Classifier: License :: OSI Approved :: GNU General Public License v3 (GPLv3)
Classifier: Natural Language :: English
Classifier: Operating System :: OS Independent
Classifier: Programming Language :: Python :: 3 :: Only
Classifier: Topic :: Software Development :: Libraries :: Python Modules
Requires-Dist: ruamel-yaml>=0.19,<=1.0
Requires-Dist: termcolor~=3.0
Requires-Dist: typing-extensions~=4.13
Requires-Python: >=3.10, <4.0
Project-URL: Documentation, https://treestamps.readthedocs.io/
Project-URL: Homepage, https://github.com/ajslater/treestamps
Project-URL: Issues, https://github.com/ajslater/treestamps/issues
Project-URL: News, https://treestamps.readthedocs.io/NEWS/
Project-URL: Source, https://github.com/ajslater/treestamps
